btrdb_admin/__init__.py
btrdb_admin/acl.py
btrdb_admin/auth.py
btrdb_admin/conn.py
btrdb_admin/core.py
btrdb_admin/exceptions.py
btrdb_admin/ingress.py
btrdb_admin/jupyter.py
btrdb_admin/version.py
btrdb_admin/grpcinterface/__init__.py
btrdb_admin/grpcinterface/admin.proto
btrdb_admin/grpcinterface/admin_pb2.py
btrdb_admin/grpcinterface/admin_pb2_grpc.py
btrdb_admin/utils/__init__.py
btrdb_admin/utils/credentials.py
btrdb_admin/utils/generic_client_interceptor.py
btrdb_admin/utils/header_manipulator_client_interceptor.py
tests/integration/__init__.py
tests/integration/test_acl.py
btrdb_admin-5.11.1.dist-info/LICENSE.txt
btrdb_admin-5.11.1.dist-info/METADATA
btrdb_admin-5.11.1.dist-info/WHEEL
btrdb_admin-5.11.1.dist-info/entry_points.txt
btrdb_admin-5.11.1.dist-info/top_level.txt
btrdb_admin-5.11.1.dist-info/RECORD
