Metadata-Version: 2.1
Name: btrdb-admin
Version: 5.11.1
Summary: Bindings to interact with the Berkeley Tree Database Admin API using gRPC.
Home-page: http://btrdb.io/
Author: Allen Leis
Author-email: allen@pingthings.io
Maintainer: Allen Leis
Maintainer-email: allen@pingthings.io
License: BSD-3-Clause
Download-URL: https://github.com/BTrDB/btrdb-admin-python/tarball/v5.11.1
Project-URL: Documentation, https://btrdb.readthedocs.io/en/latest/
Project-URL: Download, https://github.com/BTrDB/btrdb-admin-python/tarball/v5.11.1
Project-URL: Source, https://github.com/BTrDB/btrdb-admin-python
Project-URL: Tracker, https://github.com/BTrDB/btrdb-admin-python/issues
Keywords: btrdb,berkeley,timeseries,database,bindings,admin,gRPC
Platform: UNKNOWN
Classifier: Development Status :: 5 - Production/Stable
Classifier: Intended Audience :: Developers
Classifier: Intended Audience :: Information Technology
Classifier: Intended Audience :: Science/Research
Classifier: License :: OSI Approved :: BSD License
Classifier: Natural Language :: English
Classifier: Operating System :: OS Independent
Classifier: Programming Language :: Python
Classifier: Programming Language :: Python :: 3.6
Classifier: Programming Language :: Python :: 3.7
Classifier: Topic :: Database
Classifier: Topic :: Software Development :: Libraries :: Python Modules
Requires-Python: >=3.6, <4
Requires-Dist: PyYAML (==5.1.2)
Requires-Dist: grpcio (>=1.19.0)
Requires-Dist: grpcio-tools (>=1.19.0)
